ejplugins/__init__.py
ejplugins/ase_decode.py
ejplugins/cif.py
ejplugins/crystal.py
ejplugins/edict_profiling.py
ejplugins/gcube.py
ejplugins/gulp.py
ejplugins/lammps.py
ejplugins/pymatgen_decode.py
ejplugins/qespresso.py
ejplugins/test_plugins.py
ejplugins/utils.py
ejplugins/schema/__init__.py
ejplugins/schema/cif.json
ejplugins/schema/crystal_band.json
ejplugins/schema/crystal_doss.json
ejplugins/schema/crystal_out.json
ejplugins/schema/edensity.json
ejplugins/schema/qe_out.json
ejplugins/test_files/CHG_H2O_small.cube.json
ejplugins/test_files/FeS_troilite.cif.json
ejplugins/test_files/OLDcrystal.doss.f25.json
ejplugins/test_files/__init__.py
ejplugins/test_files/band.qe.out.json
ejplugins/test_files/crystal.band.f25.json
ejplugins/test_files/crystal.doss.f25.json
ejplugins/test_files/crystal.ech3.out.json
ejplugins/test_files/crystal.ech3_dat.prop3d.json
ejplugins/test_files/crystal17_spin_opt.crystal.out.json
ejplugins/test_files/crystal_pdos_spin.doss.f25.json
ejplugins/test_files/multi_atom_bulk.ech3.out.json
ejplugins/test_files/multi_atom_bulk.ech3_dat.prop3d.json
ejplugins/test_files/opt_merge_scflog.crystal.out.json
ejplugins/test_files/reaxf_noopt.gulp.out.json
ejplugins/test_files/reaxf_opt.gulp.out.json
ejplugins/test_files/relax.qe.pdos.out.json
ejplugins/test_files/scf.qe.charge.json
ejplugins/test_files/scf.qe.out.json
ejplugins/test_files/scf_and_opt.crystal.out.json
ejplugins/test_files/scf_and_opt.crystal.scflog.json
ejplugins/test_files/scf_and_opt_slab.crystal.out.json
ejplugins/test_files/scf_only.crystal.out.json
ejplugins/test_files/scf_with_fermi.qe.out.json
ejplugins/test_files/surface.qe.charge.json
ejplugins/test_files/test.qe.dos.json
ejplugins/test_files/vcrelax.qe.out.json
ejplugins-0.11.1.data/scripts/ejplugin_convert
ejplugins-0.11.1.dist-info/LICENSE
ejplugins-0.11.1.dist-info/METADATA
ejplugins-0.11.1.dist-info/WHEEL
ejplugins-0.11.1.dist-info/top_level.txt
ejplugins-0.11.1.dist-info/zip-safe
ejplugins-0.11.1.dist-info/RECORD
