Metadata-Version: 2.1
Name: ejplugins
Version: 0.11.1
Summary: parser plugins for jsonextended
Home-page: UNKNOWN
Author: Chris Sewell
Author-email: chrisj_sewell@hotmail.com
License: MIT
Keywords: python,parser,quantum-espresso,crystal,lammps,gulp
Platform: UNKNOWN
Classifier: Development Status :: 3 - Alpha
Classifier: Environment :: Console
Classifier: Environment :: Web Environment
Classifier: Intended Audience :: Science/Research
Classifier: License :: OSI Approved :: MIT License
Classifier: Operating System :: OS Independent
Classifier: Programming Language :: Python
Classifier: Programming Language :: Python :: 2
Classifier: Programming Language :: Python :: 2.7
Classifier: Programming Language :: Python :: 3
Classifier: Programming Language :: Python :: 3.2
Classifier: Programming Language :: Python :: 3.3
Classifier: Programming Language :: Python :: 3.4
Classifier: Programming Language :: Python :: 3.5
Classifier: Topic :: Scientific/Engineering :: Chemistry
Classifier: Topic :: Scientific/Engineering :: Physics
Classifier: Topic :: Software Development :: Libraries :: Python Modules
Classifier: Topic :: Utilities
Requires-Dist: jsonextended (>=0.6.4)
Requires-Dist: pathlib2
Requires-Dist: jsonschema
Requires-Dist: pint
Requires-Dist: numpy
Provides-Extra: science
Requires-Dist: pymatgen ; extra == 'science'
Requires-Dist: ase ; extra == 'science'
